GetTsite/GetTes.py
GetTsite/GetTss.py
GetTsite/__init__.py
GetTsite-0.0.3.dist-info/LICENSE
GetTsite-0.0.3.dist-info/METADATA
GetTsite-0.0.3.dist-info/WHEEL
GetTsite-0.0.3.dist-info/entry_points.txt
GetTsite-0.0.3.dist-info/top_level.txt
GetTsite-0.0.3.dist-info/RECORD
