Metadata-Version: 2.1
Name: GetTsite
Version: 0.0.3
Summary: Get gene TSS/TES site and export bed format from GTF annotation file
Home-page: https://github.com/junjunlab/GetTsite
Author: laojunjun
Author-email: 3219030654@stu.cpu.edu.cn
License: UNKNOWN
Project-URL: Bug Tracker, https://github.com/junjunlab/GetTsite/issues
Platform: UNKNOWN
Classifier: Programming Language :: Python :: 3
Classifier: License :: OSI Approved :: MIT License
Classifier: Operating System :: OS Independent
Requires-Python: >=3.6
License-File: LICENSE
